Metadata-Version: 2.1
Name: qafunnypet
Version: 0.1.1
Summary: Testing a package that can be inherit to classes that use it
Home-page: https://github.com/danielmen-mx/qafunnypet
Author: Daniel Mendez
Author-email: pablomen1131@gmail.com
Classifier: Programming Language :: Python :: 3
Classifier: License :: OSI Approved :: MIT License
Classifier: Operating System :: OS Independent
Requires-Python: >=3.6
License-File: LICENSE
